setup.py
django_booley/__init__.py
django_booley/fields.py
django_booley/validators.py
django_booley.egg-info/PKG-INFO
django_booley.egg-info/SOURCES.txt
django_booley.egg-info/dependency_links.txt
django_booley.egg-info/requires.txt
django_booley.egg-info/top_level.txt