Metadata-Version: 1.0
Name: django-booley
Version: 0.1.1
Summary: Booley integration for Django with BooleyField for models.
Home-page: https://github.com/kasappeal/django_booley
Author: Alberto Casero
Author-email: kas.appeal@gmail.com
License: MIT
Platform: UNKNOWN
